__init__.py
linux_load_execution/__init__.py
linux_load_execution/__main__.py
linux_load_execution/activation.py
linux_load_execution-0.0.1.dist-info/LICENSE
linux_load_execution-0.0.1.dist-info/METADATA
linux_load_execution-0.0.1.dist-info/WHEEL
linux_load_execution-0.0.1.dist-info/top_level.txt
linux_load_execution-0.0.1.dist-info/RECORD
