Metadata-Version: 2.2
Name: linux_load_execution
Version: 0.0.1
Summary: linux_load_execution is a Python package designed to take details like, lpar, ipaddress, script directory and script command as the input, and perform below activities
Author-email: Girija <girija.golla@ibm.com>
Classifier: Programming Language :: Python :: 3
Classifier: License :: OSI Approved :: MIT License
Classifier: Operating System :: OS Independent
Requires-Python: >=3.8
License-File: LICENSE
